[{"QueueInput/queue_size": 50.0, "train_error": 0.7455815672874451, "cross_entropy_loss": 1.7938907146453857, "validation_cost": 1.8040705919265747, "validation_error": 0.7490944552800223, "epoch_num": 1, "global_step": 897}, {"QueueInput/queue_size": 50.0, "train_error": 0.7445725798606873, "cross_entropy_loss": 1.7805016040802002, "validation_cost": 1.7938429117202759, "validation_error": 0.756338813039844, "epoch_num": 2, "global_step": 1794}, {"QueueInput/queue_size": 50.0, "train_error": 0.7629671692848206, "cross_entropy_loss": 1.7933721542358398, "validation_cost": 1.7931163311004639, "validation_error": 0.7736138200055726, "epoch_num": 3, "global_step": 2691}, {"QueueInput/queue_size": 50.0, "train_error": 0.7272094488143921, "cross_entropy_loss": 1.7710621356964111, "validation_cost": 1.7733927965164185, "validation_error": 0.7415714683755921, "epoch_num": 4, "global_step": 3588}, {"QueueInput/queue_size": 50.0, "train_error": 0.7031676769256592, "cross_entropy_loss": 1.737101674079895, "validation_cost": 1.7470327615737915, "validation_error": 0.7199777096684313, "epoch_num": 5, "global_step": 4485}, {"QueueInput/queue_size": 50.0, "train_error": 0.7009333968162537, "cross_entropy_loss": 1.7530386447906494, "validation_cost": 1.7282072305679321, "validation_error": 0.7027027027027027, "epoch_num": 6, "global_step": 5382}, {"QueueInput/queue_size": 50.0, "train_error": 0.69309002161026, "cross_entropy_loss": 1.7272452116012573, "validation_cost": 1.7159961462020874, "validation_error": 0.7011702424073558, "epoch_num": 7, "global_step": 6279}, {"QueueInput/queue_size": 50.0, "train_error": 0.6534984111785889, "cross_entropy_loss": 1.6483290195465088, "validation_cost": 1.6261258125305176, "validation_error": 0.641404290888827, "epoch_num": 8, "global_step": 7176}, {"QueueInput/queue_size": 50.0, "train_error": 0.6037271618843079, "cross_entropy_loss": 1.5335720777511597, "validation_cost": 1.5686203241348267, "validation_error": 0.6124268598495403, "epoch_num": 9, "global_step": 8073}, {"QueueInput/queue_size": 50.0, "train_error": 0.5593370199203491, "cross_entropy_loss": 1.470696210861206, "validation_cost": 1.425115704536438, "validation_error": 0.5562830872109222, "epoch_num": 10, "global_step": 8970}, {"QueueInput/queue_size": 50.0, "train_error": 0.5559523105621338, "cross_entropy_loss": 1.4370713233947754, "validation_cost": 1.4749119281768799, "validation_error": 0.5493173585957091, "epoch_num": 11, "global_step": 9867}, {"QueueInput/queue_size": 50.0, "train_error": 0.5444210171699524, "cross_entropy_loss": 1.3779963254928589, "validation_cost": 1.3843324184417725, "validation_error": 0.5337141264976316, "epoch_num": 12, "global_step": 10764}, {"QueueInput/queue_size": 50.0, "train_error": 0.5121102929115295, "cross_entropy_loss": 1.3394060134887695, "validation_cost": 1.3400334119796753, "validation_error": 0.5174143215380329, "epoch_num": 13, "global_step": 11661}]